{"_id":"multihashing-async","_rev":"18-c69a7159240642850f383ae6c23bb1e9","name":"multihashing-async","description":"multiple hash functions","dist-tags":{"latest":"0.5.1"},"versions":{"0.1.0":{"name":"multihashing-async","version":"0.1.0","description":"multiple hash functions","main":"lib/index.js","jsnext:main":"src/index.js","browser":{"./src/crypto.js":"./src/crypto-browser.js","./lib/crypto.js":"./lib/crypto-browser.js"},"scripts":{"test":"PHANTOM=off aegir-test","test:browser":"PHANTOM=off aegir-test browser","test:node":"aegir-test node","lint":"aegir-lint","release":"PHANTOM=off aegir-release","release-minor":"PHANTOM=off aegir-release minor","release-major":"PHANTOM=off aegir-release major","build":"aegir-build","coverage":"aegir-coverage","coverage-publish":"aegir-coverage publish","bench":"node benchmarks/hash.js"},"pre-commit":["lint","test"],"repository":{"type":"git","url":"git://github.com/multiformats/js-multihashing-async.git"},"keywords":["multihash"],"author":{"name":"Juan Benet","email":"juan@benet.ai","url":"http://juan.benet.ai/"},"license":"MIT","bugs":{"url":"https://github.com/multiformats/js-multihashing-async/issues"},"dependencies":{"browserify-sha3":"0.0.2","multihashes":"^0.2.0","sha3":"^1.2.0"},"devDependencies":{"aegir":"^8.1.0","benchmark":"^2.1.1","chai":"^3.5.0","pre-commit":"^1.1.2"},"homepage":"https://github.com/multiformats/js-multihashing-async","contributors":[{"name":"David Dias","email":"daviddias.p@gmail.com"},{"name":"David Dias","email":"mail@daviddias.me"},{"name":"Friedel Ziegelmayer","email":"dignifiedquire@gmail.com"},{"name":"Harlan T Wood","email":"harlantwood@users.noreply.github.com"},{"name":"Juan Batiz-Benet","email":"juan@benet.ai"},{"name":"Richard Littauer","email":"richard.littauer@gmail.com"},{"name":"npm-to-cdn-bot","email":"npmcdn-to-unpkg-bot@users.noreply.github.com","url":"by Forbes Lindesay"}],"gitHead":"99fa36b049ed2ea1c960351e80dc58e222e3afba","_id":"multihashing-async@0.1.0","_shasum":"ff396aed9cdcf27245ab913c13ce737134d4d1d3","_from":".","_npmVersion":"3.10.8","_nodeVersion":"6.6.0","_npmUser":{"name":"dignifiedquire","email":"dignifiedquire@gmail.com"},"dist":{"shasum":"ff396aed9cdcf27245ab913c13ce737134d4d1d3","tarball":"https://registry.npmjs.org/multihashing-async/-/multihashing-async-0.1.0.tgz"},"maintainers":[{"name":"dignifiedquire","email":"dignifiedquire@gmail.com"}],"_npmOperationalInternal":{"host":"packages-12-west.internal.npmjs.com","tmp":"tmp/multihashing-async-0.1.0.tgz_1475320107354_0.20771320699714124"},"directories":{}},"0.2.0":{"name":"multihashing-async","version":"0.2.0","description":"multiple hash functions","main":"src/index.js","browser":{"./src/crypto.js":"./src/crypto-browser.js"},"scripts":{"test":"aegir-test","test:browser":"aegir-test browser","test:node":"aegir-test node","lint":"aegir-lint","release":"aegir-release","release-minor":"aegir-release minor","release-major":"aegir-release major","build":"aegir-build","coverage":"aegir-coverage","coverage-publish":"aegir-coverage publish","bench":"node benchmarks/hash.js"},"pre-commit":["lint","test"],"repository":{"type":"git","url":"git://github.com/multiformats/js-multihashing-async.git"},"keywords":["multihash"],"author":{"name":"Juan Benet","email":"juan@benet.ai","url":"http://juan.benet.ai/"},"license":"MIT","bugs":{"url":"https://github.com/multiformats/js-multihashing-async/issues"},"dependencies":{"browserify-sha3":"0.0.2","multihashes":"^0.2.2","nodeify":"^1.0.0","sha3":"^1.2.0"},"devDependencies":{"aegir":"^9.0.1","benchmark":"^2.1.2","chai":"^3.5.0","pre-commit":"^1.1.3"},"engines":{"node":">=4.0.0"},"homepage":"https://github.com/multiformats/js-multihashing-async","contributors":[{"name":"David Dias","email":"daviddias.p@gmail.com"},{"name":"David Dias","email":"mail@daviddias.me"},{"name":"Friedel Ziegelmayer","email":"dignifiedquire@gmail.com"},{"name":"Harlan T Wood","email":"harlantwood@users.noreply.github.com"},{"name":"Juan Batiz-Benet","email":"juan@benet.ai"},{"name":"Richard Littauer","email":"richard.littauer@gmail.com"},{"name":"npm-to-cdn-bot","email":"npmcdn-to-unpkg-bot@users.noreply.github.com","url":"by Forbes Lindesay"}],"gitHead":"00c49de9a9e6a952deb43e955e4757ae45f04592","_id":"multihashing-async@0.2.0","_shasum":"8dec195a20fe402cca38e2728d693607d1c5a37b","_from":".","_npmVersion":"3.10.8","_nodeVersion":"6.9.1","_npmUser":{"name":"daviddias","email":"daviddias.p@gmail.com"},"maintainers":[{"name":"daviddias","email":"daviddias.p@gmail.com"},{"name":"dignifiedquire","email":"dignifiedquire@gmail.com"}],"dist":{"shasum":"8dec195a20fe402cca38e2728d693607d1c5a37b","tarball":"https://registry.npmjs.org/multihashing-async/-/multihashing-async-0.2.0.tgz"},"_npmOperationalInternal":{"host":"packages-18-east.internal.npmjs.com","tmp":"tmp/multihashing-async-0.2.0.tgz_1478158779132_0.21538168285042048"},"directories":{}},"0.3.0":{"name":"multihashing-async","version":"0.3.0","description":"multiple hash functions","main":"src/index.js","browser":{"./src/crypto-sha1-2.js":"./src/crypto-sha1-2-browser.js"},"scripts":{"test":"aegir-test","test:browser":"aegir-test browser","test:node":"aegir-test node","lint":"aegir-lint","release":"aegir-release","release-minor":"aegir-release minor","release-major":"aegir-release major","build":"aegir-build","coverage":"aegir-coverage","coverage-publish":"aegir-coverage publish","bench":"node benchmarks/hash.js"},"pre-commit":["lint","test"],"repository":{"type":"git","url":"git://github.com/multiformats/js-multihashing-async.git"},"keywords":["multihash"],"author":{"name":"Juan Benet","email":"juan@benet.ai","url":"http://juan.benet.ai/"},"license":"MIT","bugs":{"url":"https://github.com/multiformats/js-multihashing-async/issues"},"dependencies":{"async":"^2.1.4","js-sha3":"^0.5.5","multihashes":"^0.3.0","nodeify":"^1.0.0"},"devDependencies":{"aegir":"^9.1.2","benchmark":"^2.1.2","chai":"^3.5.0","pre-commit":"^1.1.3"},"engines":{"node":">=4.0.0"},"homepage":"https://github.com/multiformats/js-multihashing-async","contributors":[{"name":"David Dias","email":"daviddias.p@gmail.com"},{"name":"David Dias","email":"mail@daviddias.me"},{"name":"Friedel Ziegelmayer","email":"dignifiedquire@gmail.com"},{"name":"Harlan T Wood","email":"harlantwood@users.noreply.github.com"},{"name":"Juan Batiz-Benet","email":"juan@benet.ai"},{"name":"Richard Littauer","email":"richard.littauer@gmail.com"},{"name":"npm-to-cdn-bot","email":"npmcdn-to-unpkg-bot@users.noreply.github.com","url":"by Forbes Lindesay"}],"gitHead":"0d94dfcba82f5f330a6eeb8c0b2a8c52ad1f4d42","_id":"multihashing-async@0.3.0","_shasum":"64995118d8183b1291a559478772979f80aaf917","_from":".","_npmVersion":"4.0.3","_nodeVersion":"7.2.0","_npmUser":{"name":"dignifiedquire","email":"dignifiedquire@gmail.com"},"dist":{"shasum":"64995118d8183b1291a559478772979f80aaf917","tarball":"https://registry.npmjs.org/multihashing-async/-/multihashing-async-0.3.0.tgz"},"maintainers":[{"name":"daviddias","email":"daviddias.p@gmail.com"},{"name":"dignifiedquire","email":"dignifiedquire@gmail.com"}],"_npmOperationalInternal":{"host":"packages-18-east.internal.npmjs.com","tmp":"tmp/multihashing-async-0.3.0.tgz_1480438983010_0.48173042107373476"},"directories":{}},"0.4.0":{"name":"multihashing-async","version":"0.4.0","description":"multiple hash functions","main":"src/index.js","browser":{"./src/crypto-sha1-2.js":"./src/crypto-sha1-2-browser.js"},"scripts":{"test":"aegir-test --webworker","test:browser":"aegir-test browser --webworker","test:node":"aegir-test node","lint":"aegir-lint","docs":"aegir-docs","release":"aegir-release --docs --webworker","release-minor":"aegir-release minor --docs --webworker","release-major":"aegir-release major --docs --webworker","build":"aegir-build","coverage":"aegir-coverage","coverage-publish":"aegir-coverage publish","bench":"node benchmarks/hash.js"},"pre-commit":["lint","test"],"repository":{"type":"git","url":"git://github.com/multiformats/js-multihashing-async.git"},"keywords":["multihash"],"author":{"name":"Juan Benet","email":"juan@benet.ai","url":"http://juan.benet.ai/"},"license":"MIT","bugs":{"url":"https://github.com/multiformats/js-multihashing-async/issues"},"dependencies":{"async":"^2.1.4","js-sha3":"^0.5.7","multihashes":"^0.3.2","murmurhash3js":"^3.0.1","nodeify":"^1.0.0"},"devDependencies":{"aegir":"^9.4.0","benchmark":"^2.1.3","chai":"^3.5.0","pre-commit":"^1.2.2"},"engines":{"node":">=4.0.0"},"homepage":"https://github.com/multiformats/js-multihashing-async","contributors":[{"name":"David Dias","email":"daviddias.p@gmail.com"},{"name":"David Dias","email":"mail@daviddias.me"},{"name":"Friedel Ziegelmayer","email":"dignifiedquire@gmail.com"},{"name":"Harlan T Wood","email":"harlantwood@users.noreply.github.com"},{"name":"Juan Batiz-Benet","email":"juan@benet.ai"},{"name":"Pedro Teixeira","email":"i@pgte.me"},{"name":"Richard Littauer","email":"richard.littauer@gmail.com"},{"name":"npm-to-cdn-bot","email":"npmcdn-to-unpkg-bot@users.noreply.github.com","url":"by Forbes Lindesay"}],"gitHead":"68f4cb26407d27f674dfd685c5538b6176bb8083","_id":"multihashing-async@0.4.0","_shasum":"b274872a0bf70bec113dda928933dc97bc298ece","_from":".","_npmVersion":"4.0.3","_nodeVersion":"7.2.1","_npmUser":{"name":"dignifiedquire","email":"dignifiedquire@gmail.com"},"dist":{"shasum":"b274872a0bf70bec113dda928933dc97bc298ece","tarball":"https://registry.npmjs.org/multihashing-async/-/multihashing-async-0.4.0.tgz"},"maintainers":[{"name":"daviddias","email":"daviddias.p@gmail.com"},{"name":"dignifiedquire","email":"dignifiedquire@gmail.com"}],"_npmOperationalInternal":{"host":"packages-12-west.internal.npmjs.com","tmp":"tmp/multihashing-async-0.4.0.tgz_1485515640330_0.8893461388070136"},"directories":{}},"0.4.1":{"name":"multihashing-async","version":"0.4.1","description":"multiple hash functions","main":"src/index.js","browser":{"./src/crypto-sha1-2.js":"./src/crypto-sha1-2-browser.js"},"scripts":{"test":"aegir-test","test:browser":"aegir-test browser","test:node":"aegir-test node","lint":"aegir-lint","docs":"aegir-docs","release":"aegir-release --docs","release-minor":"aegir-release minor --docs","release-major":"aegir-release major --docs","build":"aegir-build","coverage":"aegir-coverage","coverage-publish":"aegir-coverage publish","bench":"node benchmarks/hash.js"},"pre-commit":["lint","test"],"repository":{"type":"git","url":"git://github.com/multiformats/js-multihashing-async.git"},"keywords":["multihash"],"author":{"name":"Juan Benet","email":"juan@benet.ai","url":"http://juan.benet.ai/"},"license":"MIT","bugs":{"url":"https://github.com/multiformats/js-multihashing-async/issues"},"dependencies":{"async":"^2.1.4","js-sha3":"^0.5.7","multihashes":"^0.3.2","murmurhash3js":"^3.0.1","nodeify":"^1.0.0"},"devDependencies":{"aegir":"^10.0.0","benchmark":"^2.1.3","chai":"^3.5.0","pre-commit":"^1.2.2"},"engines":{"node":">=4.0.0"},"homepage":"https://github.com/multiformats/js-multihashing-async","contributors":[{"name":"David Dias","email":"daviddias.p@gmail.com"},{"name":"David Dias","email":"mail@daviddias.me"},{"name":"Dmitriy Ryajov","email":"dryajov@gmail.com"},{"name":"Friedel Ziegelmayer","email":"dignifiedquire@gmail.com"},{"name":"Harlan T Wood","email":"harlantwood@users.noreply.github.com"},{"name":"Juan Batiz-Benet","email":"juan@benet.ai"},{"name":"Pedro Teixeira","email":"i@pgte.me"},{"name":"Richard Littauer","email":"richard.littauer@gmail.com"},{"name":"npm-to-cdn-bot","email":"npmcdn-to-unpkg-bot@users.noreply.github.com","url":"by Forbes Lindesay"}],"gitHead":"4829db01207edc5b79fcbc17d2ba7140e50caec0","_id":"multihashing-async@0.4.1","_shasum":"e97fc5bbbab839ac2b0389e9179830adabb16462","_from":".","_npmVersion":"4.0.3","_nodeVersion":"7.2.1","_npmUser":{"name":"dignifiedquire","email":"dignifiedquire@gmail.com"},"dist":{"shasum":"e97fc5bbbab839ac2b0389e9179830adabb16462","tarball":"https://registry.npmjs.org/multihashing-async/-/multihashing-async-0.4.1.tgz"},"maintainers":[{"name":"daviddias","email":"daviddias.p@gmail.com"},{"name":"dignifiedquire","email":"dignifiedquire@gmail.com"}],"_npmOperationalInternal":{"host":"packages-12-west.internal.npmjs.com","tmp":"tmp/multihashing-async-0.4.1.tgz_1486588086355_0.4668246656656265"},"directories":{}},"0.4.2":{"name":"multihashing-async","version":"0.4.2","description":"multiple hash functions","main":"src/index.js","browser":{"./src/crypto-sha1-2.js":"./src/crypto-sha1-2-browser.js"},"scripts":{"test":"aegir-test","test:browser":"aegir-test browser","test:node":"aegir-test node","lint":"aegir-lint","docs":"aegir-docs","release":"aegir-release --docs","release-minor":"aegir-release minor --docs","release-major":"aegir-release major --docs","build":"aegir-build","coverage":"aegir-coverage","coverage-publish":"aegir-coverage publish","bench":"node benchmarks/hash.js"},"pre-commit":["lint","test"],"repository":{"type":"git","url":"git://github.com/multiformats/js-multihashing-async.git"},"keywords":["multihash"],"author":{"name":"Juan Benet","email":"juan@benet.ai","url":"http://juan.benet.ai/"},"license":"MIT","bugs":{"url":"https://github.com/multiformats/js-multihashing-async/issues"},"dependencies":{"multihashes":"~0.3.3","async":"^2.1.4","js-sha3":"^0.5.7","murmurhash3js":"^3.0.1","nodeify":"^1.0.0"},"devDependencies":{"aegir":"^10.0.0","benchmark":"^2.1.3","chai":"^3.5.0","pre-commit":"^1.2.2"},"engines":{"node":">=4.0.0","npm":">=3.0.0"},"homepage":"https://github.com/multiformats/js-multihashing-async","contributors":[{"name":"David Dias","email":"daviddias.p@gmail.com"},{"name":"David Dias","email":"mail@daviddias.me"},{"name":"Dmitriy Ryajov","email":"dryajov@gmail.com"},{"name":"Friedel Ziegelmayer","email":"dignifiedquire@gmail.com"},{"name":"Harlan T Wood","email":"harlantwood@users.noreply.github.com"},{"name":"Juan Batiz-Benet","email":"juan@benet.ai"},{"name":"Pedro Teixeira","email":"i@pgte.me"},{"name":"Richard Littauer","email":"richard.littauer@gmail.com"},{"name":"npm-to-cdn-bot","email":"npmcdn-to-unpkg-bot@users.noreply.github.com","url":"by Forbes Lindesay"}],"gitHead":"237a7701e9d8b9ae249d743f1c037bf31c816ed4","_id":"multihashing-async@0.4.2","_shasum":"0ef22484375f69ba29823d23931881aff172e612","_from":".","_npmVersion":"3.10.8","_nodeVersion":"6.9.1","_npmUser":{"name":"daviddias","email":"daviddias.p@gmail.com"},"dist":{"shasum":"0ef22484375f69ba29823d23931881aff172e612","tarball":"https://registry.npmjs.org/multihashing-async/-/multihashing-async-0.4.2.tgz"},"maintainers":[{"name":"daviddias","email":"daviddias.p@gmail.com"},{"name":"dignifiedquire","email":"dignifiedquire@gmail.com"}],"_npmOperationalInternal":{"host":"packages-12-west.internal.npmjs.com","tmp":"tmp/multihashing-async-0.4.2.tgz_1486655468541_0.9199695901479572"},"directories":{}},"0.4.3":{"name":"multihashing-async","version":"0.4.3","description":"multiple hash functions","main":"src/index.js","browser":{"./src/crypto-sha1-2.js":"./src/crypto-sha1-2-browser.js"},"scripts":{"test":"aegir-test","test:browser":"aegir-test browser","test:node":"aegir-test node","lint":"aegir-lint","docs":"aegir-docs","release":"aegir-release --docs","release-minor":"aegir-release minor --docs","release-major":"aegir-release major --docs","build":"aegir-build","coverage":"aegir-coverage","coverage-publish":"aegir-coverage publish","bench":"node benchmarks/hash.js"},"pre-commit":["lint","test"],"repository":{"type":"git","url":"git://github.com/multiformats/js-multihashing-async.git"},"keywords":["multihash"],"author":{"name":"Juan Benet","email":"juan@benet.ai","url":"http://juan.benet.ai/"},"license":"MIT","bugs":{"url":"https://github.com/multiformats/js-multihashing-async/issues"},"dependencies":{"async":"^2.1.5","blakejs":"^1.0.1","js-sha3":"^0.5.7","multihashes":"~0.4.3","murmurhash3js":"^3.0.1","nodeify":"^1.0.0"},"devDependencies":{"aegir":"^10.0.0","benchmark":"^2.1.3","chai":"^3.5.0","pre-commit":"^1.2.2"},"engines":{"node":">=4.0.0","npm":">=3.0.0"},"homepage":"https://github.com/multiformats/js-multihashing-async","contributors":[{"name":"David Dias","email":"daviddias.p@gmail.com"},{"name":"David Dias","email":"mail@daviddias.me"},{"name":"Dmitriy Ryajov","email":"dryajov@gmail.com"},{"name":"Friedel Ziegelmayer","email":"dignifiedquire@gmail.com"},{"name":"Harlan T Wood","email":"harlantwood@users.noreply.github.com"},{"name":"Juan Batiz-Benet","email":"juan@benet.ai"},{"name":"Pedro Teixeira","email":"i@pgte.me"},{"name":"Richard Littauer","email":"richard.littauer@gmail.com"},{"name":"npm-to-cdn-bot","email":"npmcdn-to-unpkg-bot@users.noreply.github.com","url":"by Forbes Lindesay"}],"gitHead":"b65cdd71806df9ec1668cb7bccb968de1426dcaa","_id":"multihashing-async@0.4.3","_shasum":"d902d53624f528d492da7a7b10ed0e4f8f5758b6","_from":".","_npmVersion":"4.0.3","_nodeVersion":"7.2.1","_npmUser":{"name":"dignifiedquire","email":"dignifiedquire@gmail.com"},"dist":{"shasum":"d902d53624f528d492da7a7b10ed0e4f8f5758b6","tarball":"https://registry.npmjs.org/multihashing-async/-/multihashing-async-0.4.3.tgz"},"maintainers":[{"name":"daviddias","email":"daviddias.p@gmail.com"},{"name":"dignifiedquire","email":"dignifiedquire@gmail.com"}],"_npmOperationalInternal":{"host":"packages-18-east.internal.npmjs.com","tmp":"tmp/multihashing-async-0.4.3.tgz_1487937168950_0.5896622131112963"},"directories":{}},"0.4.4":{"name":"multihashing-async","version":"0.4.4","description":"multiple hash functions","main":"src/index.js","browser":{"./src/crypto-sha1-2.js":"./src/crypto-sha1-2-browser.js"},"scripts":{"test":"aegir-test","test:browser":"aegir-test browser","test:node":"aegir-test node","lint":"aegir-lint","docs":"aegir-docs","release":"aegir-release --docs","release-minor":"aegir-release minor --docs","release-major":"aegir-release major --docs","build":"aegir-build","coverage":"aegir-coverage","coverage-publish":"aegir-coverage publish","bench":"node benchmarks/hash.js"},"pre-commit":["lint","test"],"repository":{"type":"git","url":"git://github.com/multiformats/js-multihashing-async.git"},"keywords":["multihash"],"author":{"name":"Juan Benet","email":"juan@benet.ai","url":"http://juan.benet.ai/"},"license":"MIT","bugs":{"url":"https://github.com/multiformats/js-multihashing-async/issues"},"dependencies":{"async":"^2.1.5","blakejs":"^1.0.1","js-sha3":"^0.5.7","multihashes":"~0.4.4","murmurhash3js":"^3.0.1","nodeify":"^1.0.1"},"devDependencies":{"aegir":"^11.0.0","benchmark":"^2.1.3","chai":"^3.5.0","pre-commit":"^1.2.2"},"engines":{"node":">=4.0.0","npm":">=3.0.0"},"homepage":"https://github.com/multiformats/js-multihashing-async","contributors":[{"name":"David Dias","email":"daviddias.p@gmail.com"},{"name":"David Dias","email":"mail@daviddias.me"},{"name":"Dmitriy Ryajov","email":"dryajov@gmail.com"},{"name":"Friedel Ziegelmayer","email":"dignifiedquire@gmail.com"},{"name":"Harlan T Wood","email":"harlantwood@users.noreply.github.com"},{"name":"Juan Batiz-Benet","email":"juan@benet.ai"},{"name":"Mitar","email":"mitar.github@tnode.com"},{"name":"Pedro Teixeira","email":"i@pgte.me"},{"name":"Richard Littauer","email":"richard.littauer@gmail.com"},{"name":"npm-to-cdn-bot","email":"npmcdn-to-unpkg-bot@users.noreply.github.com","url":"by Forbes Lindesay"}],"gitHead":"c72f1c199087c52e6b91ff07aa87039c1a27b4ce","_id":"multihashing-async@0.4.4","_shasum":"e48fe33a85f00eb24cd7c3e450777a1e13e92dd0","_from":".","_npmVersion":"3.10.8","_nodeVersion":"6.9.1","_npmUser":{"name":"daviddias","email":"daviddias.p@gmail.com"},"dist":{"shasum":"e48fe33a85f00eb24cd7c3e450777a1e13e92dd0","tarball":"https://registry.npmjs.org/multihashing-async/-/multihashing-async-0.4.4.tgz"},"maintainers":[{"name":"daviddias","email":"daviddias.p@gmail.com"},{"name":"dignifiedquire","email":"dignifiedquire@gmail.com"}],"_npmOperationalInternal":{"host":"packages-18-east.internal.npmjs.com","tmp":"tmp/multihashing-async-0.4.4.tgz_1489677150673_0.2986808742862195"},"directories":{}},"0.4.5":{"name":"multihashing-async","version":"0.4.5","description":"multiple hash functions","main":"src/index.js","browser":{"./src/crypto-sha1-2.js":"./src/crypto-sha1-2-browser.js"},"scripts":{"test":"aegir-test","test:browser":"aegir-test browser","test:node":"aegir-test node","lint":"aegir-lint","docs":"aegir-docs","release":"aegir-release --docs","release-minor":"aegir-release minor --docs","release-major":"aegir-release major --docs","build":"aegir-build","coverage":"aegir-coverage","coverage-publish":"aegir-coverage publish","bench":"node benchmarks/hash.js"},"pre-commit":["lint","test"],"repository":{"type":"git","url":"git://github.com/multiformats/js-multihashing-async.git"},"keywords":["multihash"],"author":{"name":"Juan Benet","email":"juan@benet.ai","url":"http://juan.benet.ai/"},"license":"MIT","bugs":{"url":"https://github.com/multiformats/js-multihashing-async/issues"},"dependencies":{"async":"^2.1.5","blakejs":"^1.0.1","js-sha3":"^0.5.7","multihashes":"~0.4.5","murmurhash3js":"^3.0.1","nodeify":"^1.0.1"},"devDependencies":{"aegir":"^11.0.1","benchmark":"^2.1.3","chai":"^3.5.0","dirty-chai":"^1.2.2","pre-commit":"^1.2.2"},"engines":{"node":">=4.0.0","npm":">=3.0.0"},"homepage":"https://github.com/multiformats/js-multihashing-async","contributors":[{"name":"David Dias","email":"daviddias.p@gmail.com"},{"name":"David Dias","email":"mail@daviddias.me"},{"name":"Dmitriy Ryajov","email":"dryajov@gmail.com"},{"name":"Friedel Ziegelmayer","email":"dignifiedquire@gmail.com"},{"name":"Harlan T Wood","email":"harlantwood@users.noreply.github.com"},{"name":"Juan Batiz-Benet","email":"juan@benet.ai"},{"name":"Mitar","email":"mitar.github@tnode.com"},{"name":"Pedro Teixeira","email":"i@pgte.me"},{"name":"Richard Littauer","email":"richard.littauer@gmail.com"},{"name":"npm-to-cdn-bot","email":"npmcdn-to-unpkg-bot@users.noreply.github.com","url":"by Forbes Lindesay"}],"gitHead":"8ebf3482e34a328e251dcd307fe32fa13e3e625f","_id":"multihashing-async@0.4.5","_shasum":"e94b408a68c36c393180146e3fad9126108eb6a9","_from":".","_npmVersion":"3.10.10","_nodeVersion":"6.10.0","_npmUser":{"name":"daviddias","email":"daviddias.p@gmail.com"},"dist":{"shasum":"e94b408a68c36c393180146e3fad9126108eb6a9","tarball":"https://registry.npmjs.org/multihashing-async/-/multihashing-async-0.4.5.tgz"},"maintainers":[{"name":"daviddias","email":"daviddias.p@gmail.com"},{"name":"dignifiedquire","email":"dignifiedquire@gmail.com"}],"_npmOperationalInternal":{"host":"packages-12-west.internal.npmjs.com","tmp":"tmp/multihashing-async-0.4.5.tgz_1490272342124_0.33111967984586954"},"directories":{}},"0.4.6":{"name":"multihashing-async","version":"0.4.6","description":"multiple hash functions","main":"src/index.js","browser":{"./src/crypto-sha1-2.js":"./src/crypto-sha1-2-browser.js"},"scripts":{"test":"aegir-test","test:browser":"aegir-test browser","test:node":"aegir-test node","lint":"aegir-lint","docs":"aegir-docs","release":"aegir-release --docs","release-minor":"aegir-release minor --docs","release-major":"aegir-release major --docs","build":"aegir-build","coverage":"aegir-coverage","coverage-publish":"aegir-coverage publish","bench":"node benchmarks/hash.js"},"pre-commit":["lint","test"],"repository":{"type":"git","url":"git://github.com/multiformats/js-multihashing-async.git"},"keywords":["multihash"],"author":{"name":"Juan Benet","email":"juan@benet.ai","url":"http://juan.benet.ai/"},"license":"MIT","bugs":{"url":"https://github.com/multiformats/js-multihashing-async/issues"},"dependencies":{"async":"^2.5.0","blakejs":"^1.1.0","js-sha3":"^0.6.1","multihashes":"~0.4.5","murmurhash3js":"^3.0.1","nodeify":"^1.0.1"},"devDependencies":{"aegir":"^11.0.2","benchmark":"^2.1.4","chai":"^4.1.0","dirty-chai":"^2.0.1","pre-commit":"^1.2.2"},"engines":{"node":">=4.0.0","npm":">=3.0.0"},"homepage":"https://github.com/multiformats/js-multihashing-async","contributors":[{"name":"David Dias","email":"daviddias.p@gmail.com"},{"name":"David Dias","email":"mail@daviddias.me"},{"name":"Dmitriy Ryajov","email":"dryajov@gmail.com"},{"name":"Friedel Ziegelmayer","email":"dignifiedquire@gmail.com"},{"name":"Harlan T Wood","email":"harlantwood@users.noreply.github.com"},{"name":"Juan Batiz-Benet","email":"juan@benet.ai"},{"name":"Mitar","email":"mitar.github@tnode.com"},{"name":"Pedro Teixeira","email":"i@pgte.me"},{"name":"Richard Littauer","email":"richard.littauer@gmail.com"},{"name":"npm-to-cdn-bot","email":"npmcdn-to-unpkg-bot@users.noreply.github.com","url":"by Forbes Lindesay"}],"gitHead":"4c4001d814402c6d25542e93b44e957a581ed862","_id":"multihashing-async@0.4.6","_shasum":"b01c8d0745ccac085afd7a9a5e8182f73505d7f7","_from":".","_npmVersion":"4.2.0","_nodeVersion":"7.10.0","_npmUser":{"name":"daviddias","email":"daviddias.p@gmail.com"},"dist":{"shasum":"b01c8d0745ccac085afd7a9a5e8182f73505d7f7","tarball":"https://registry.npmjs.org/multihashing-async/-/multihashing-async-0.4.6.tgz"},"maintainers":[{"name":"daviddias","email":"daviddias.p@gmail.com"},{"name":"dignifiedquire","email":"dignifiedquire@gmail.com"}],"_npmOperationalInternal":{"host":"s3://npm-registry-packages","tmp":"tmp/multihashing-async-0.4.6.tgz_1500653667350_0.046663952292874455"},"directories":{}},"0.4.7":{"name":"multihashing-async","version":"0.4.7","description":"multiple hash functions","main":"src/index.js","browser":{"./src/crypto-sha1-2.js":"./src/crypto-sha1-2-browser.js"},"scripts":{"test":"aegir-test","test:browser":"aegir-test browser","test:node":"aegir-test node","lint":"aegir-lint","docs":"aegir-docs","release":"aegir-release --docs","release-minor":"aegir-release minor --docs","release-major":"aegir-release major --docs","build":"aegir-build","coverage":"aegir-coverage","coverage-publish":"aegir-coverage publish","bench":"node benchmarks/hash.js"},"pre-commit":["lint","test"],"repository":{"type":"git","url":"git://github.com/multiformats/js-multihashing-async.git"},"keywords":["multihash"],"author":{"name":"Juan Benet","email":"juan@benet.ai","url":"http://juan.benet.ai/"},"license":"MIT","bugs":{"url":"https://github.com/multiformats/js-multihashing-async/issues"},"dependencies":{"async":"^2.5.0","blakejs":"^1.1.0","js-sha3":"^0.6.1","multihashes":"~0.4.12","murmurhash3js":"^3.0.1","nodeify":"^1.0.1"},"devDependencies":{"aegir":"^11.0.2","benchmark":"^2.1.4","chai":"^4.1.2","dirty-chai":"^2.0.1","pre-commit":"^1.2.2"},"engines":{"node":">=4.0.0","npm":">=3.0.0"},"homepage":"https://github.com/multiformats/js-multihashing-async","contributors":[{"name":"David Dias","email":"daviddias.p@gmail.com"},{"name":"David Dias","email":"mail@daviddias.me"},{"name":"Dmitriy Ryajov","email":"dryajov@gmail.com"},{"name":"Friedel Ziegelmayer","email":"dignifiedquire@gmail.com"},{"name":"Harlan T Wood","email":"harlantwood@users.noreply.github.com"},{"name":"Juan Batiz-Benet","email":"juan@benet.ai"},{"name":"Mitar","email":"mitar.github@tnode.com"},{"name":"Pedro Teixeira","email":"i@pgte.me"},{"name":"Richard Littauer","email":"richard.littauer@gmail.com"},{"name":"npm-to-cdn-bot","email":"npmcdn-to-unpkg-bot@users.noreply.github.com","url":"by Forbes Lindesay"}],"gitHead":"e1efcf6065ab742296905c82ef8329e1ffa6e27f","_id":"multihashing-async@0.4.7","_npmVersion":"5.5.1","_nodeVersion":"8.4.0","_npmUser":{"name":"daviddias","email":"daviddias.p@gmail.com"},"dist":{"integrity":"sha512-jjW5r2M3zS7YZmylUH1FmrckD6pQXMeMQTAvTJyo83hfTZ3B6fyph7AvHaDdr3M6c4zlmvSCM8jpEItjJ9dxuw==","shasum":"b6c4a6854e64c3aa08700b4b9db6cfa18c88a828","tarball":"https://registry.npmjs.org/multihashing-async/-/multihashing-async-0.4.7.tgz"},"maintainers":[{"name":"daviddias","email":"daviddias.p@gmail.com"},{"name":"dignifiedquire","email":"dignifiedquire@gmail.com"}],"_npmOperationalInternal":{"host":"s3://npm-registry-packages","tmp":"tmp/multihashing-async-0.4.7.tgz_1508500462914_0.7910483737941831"},"directories":{}},"0.4.8":{"name":"multihashing-async","version":"0.4.8","description":"multiple hash functions","main":"src/index.js","browser":{"./src/crypto-sha1-2.js":"./src/crypto-sha1-2-browser.js"},"scripts":{"test":"aegir test","test:browser":"aegir test -t browser","test:node":"aegir test -t node","lint":"aegir lint","docs":"aegir docs","release":"aegir release --docs","release-minor":"aegir release minor --docs","release-major":"aegir release major --docs","build":"aegir build","coverage":"aegir coverage","coverage-publish":"aegir coverage publish","bench":"node benchmarks/hash.js"},"pre-commit":["lint","test"],"repository":{"type":"git","url":"git://github.com/multiformats/js-multihashing-async.git"},"keywords":["multihash"],"author":{"name":"Juan Benet","email":"juan@benet.ai","url":"http://juan.benet.ai/"},"license":"MIT","bugs":{"url":"https://github.com/multiformats/js-multihashing-async/issues"},"dependencies":{"async":"^2.6.0","blakejs":"^1.1.0","js-sha3":"^0.7.0","multihashes":"~0.4.13","murmurhash3js":"^3.0.1","nodeify":"^1.0.1"},"devDependencies":{"aegir":"^13.0.5","benchmark":"^2.1.4","chai":"^4.1.2","dirty-chai":"^2.0.1","pre-commit":"^1.2.2"},"engines":{"node":">=6.0.0","npm":">=3.0.0"},"homepage":"https://github.com/multiformats/js-multihashing-async","contributors":[{"name":"David Dias","email":"daviddias.p@gmail.com"},{"name":"David Dias","email":"mail@daviddias.me"},{"name":"Dmitriy Ryajov","email":"dryajov@gmail.com"},{"name":"Friedel Ziegelmayer","email":"dignifiedquire@gmail.com"},{"name":"Harlan T Wood","email":"harlantwood@users.noreply.github.com"},{"name":"Juan Batiz-Benet","email":"juan@benet.ai"},{"name":"Mitar","email":"mitar.github@tnode.com"},{"name":"Pedro Teixeira","email":"i@pgte.me"},{"name":"Richard Littauer","email":"richard.littauer@gmail.com"},{"name":"Victor Bjelkholm","email":"victorbjelkholm@gmail.com"},{"name":"Volker Mische","email":"volker.mische@gmail.com"},{"name":"npm-to-cdn-bot","email":"npmcdn-to-unpkg-bot@users.noreply.github.com","url":"by Forbes Lindesay"}],"gitHead":"e0fc9226033a7f887c7e4559e1a4b592aab80069","_id":"multihashing-async@0.4.8","_npmVersion":"5.6.0","_nodeVersion":"9.4.0","_npmUser":{"name":"daviddias","email":"daviddias.p@gmail.com"},"dist":{"integrity":"sha512-LCc4lfxmTJOHKIjZjFNgvmfB6nXS/ErLInT9uwU8udFrRm2PH+aTPk3mfCREKmCiSHOlCWiv2O8rlnBx+OjlMw==","shasum":"41572b25a8fc68eb318b8562409fdd721a727ea1","tarball":"https://registry.npmjs.org/multihashing-async/-/multihashing-async-0.4.8.tgz","fileCount":19,"unpackedSize":527383},"maintainers":[{"name":"daviddias","email":"daviddias.p@gmail.com"},{"name":"dignifiedquire","email":"dignifiedquire@gmail.com"}],"directories":{},"_npmOperationalInternal":{"host":"s3://npm-registry-packages","tmp":"tmp/multihashing-async_0.4.8_1519732718023_0.13975339205447734"}},"0.5.0":{"name":"multihashing-async","version":"0.5.0","description":"multiple hash functions","main":"src/index.js","browser":{"./src/crypto-sha1-2.js":"./src/crypto-sha1-2-browser.js"},"scripts":{"test":"aegir test","test:browser":"aegir test -t browser","test:node":"aegir test -t node","lint":"aegir lint","docs":"aegir docs","release":"aegir release --docs","release-minor":"aegir release --type minor --docs","release-major":"aegir release --type major --docs","build":"aegir build","coverage":"aegir coverage","coverage-publish":"aegir coverage publish","bench":"node benchmarks/hash.js"},"pre-commit":["lint","test"],"repository":{"type":"git","url":"git://github.com/multiformats/js-multihashing-async.git"},"keywords":["multihash"],"author":{"name":"Juan Benet","email":"juan@benet.ai","url":"http://juan.benet.ai/"},"license":"MIT","bugs":{"url":"https://github.com/multiformats/js-multihashing-async/issues"},"dependencies":{"async":"^2.6.0","blakejs":"^1.1.0","js-sha3":"^0.7.0","multihashes":"~0.4.13","murmurhash3js":"^3.0.1","nodeify":"^1.0.1"},"devDependencies":{"aegir":"^13.1.0","benchmark":"^2.1.4","chai":"^4.1.2","dirty-chai":"^2.0.1","pre-commit":"^1.2.2"},"engines":{"node":">=6.0.0","npm":">=3.0.0"},"homepage":"https://github.com/multiformats/js-multihashing-async","contributors":[{"name":"David Dias","email":"daviddias.p@gmail.com"},{"name":"David Dias","email":"mail@daviddias.me"},{"name":"Dmitriy Ryajov","email":"dryajov@gmail.com"},{"name":"Friedel Ziegelmayer","email":"dignifiedquire@gmail.com"},{"name":"Harlan T Wood","email":"harlantwood@users.noreply.github.com"},{"name":"Juan Batiz-Benet","email":"juan@benet.ai"},{"name":"Mitar","email":"mitar.github@tnode.com"},{"name":"Pedro Teixeira","email":"i@pgte.me"},{"name":"Richard Littauer","email":"richard.littauer@gmail.com"},{"name":"Richard Schneider","email":"makaretu@gmail.com"},{"name":"Victor Bjelkholm","email":"victorbjelkholm@gmail.com"},{"name":"Volker Mische","email":"volker.mische@gmail.com"},{"name":"npm-to-cdn-bot","email":"npmcdn-to-unpkg-bot@users.noreply.github.com","url":"by Forbes Lindesay"}],"gitHead":"e0a20aff36fccb16ec98efe55ed7abc46657f6a1","_id":"multihashing-async@0.5.0","_npmVersion":"5.6.0","_nodeVersion":"8.11.1","_npmUser":{"name":"daviddias","email":"mail@daviddias.me"},"dist":{"integrity":"sha512-fi1FK4H3yMT5pVibC8ZPtDciEaX/xpr+FyiMnnH6idv8VtZ24hB/stDrxIIomxi8px4KwqZRhqko4gmq1YyUrQ==","shasum":"e749eea9abee52a86d48de9f61ee02d905a3783a","tarball":"https://registry.npmjs.org/multihashing-async/-/multihashing-async-0.5.0.tgz","fileCount":19,"unpackedSize":495380,"npm-signature":"-----BEGIN PGP SIGNATURE-----\r\nVersion: OpenPGP.js v3.0.4\r\nComment: https://openpgpjs.org\r\n\r\nwsFcBAEBCAAQBQJa8BP5CRA9TVsSAnZWagAAk/IP/RFqkkCs71MVS8P6FRP6\n9w2b938utPJCCbFN9J2cvnFVkzIfx9zmBCMRNIJ050XwPzILVjXoWe4mZvXG\nIT7BnA8Yh02CQEsdk1ugEctCHDbWQqLQP4JmbwDI607NebPRyW0dhBzljkfM\n8qUEImiNFGMRXr2rUtJaaSUQ8buWeOhO/taFZb4Gafp9d38TuIe/o4BfENaP\n6rfdgVXtFwLD90S55DU8pdpun6TGbW1xa59ELmreqwFDy8evcCoF8UIRt2BF\nuvjWYTA1SSmAQXFc/KFK/poqYG251ZK+RdItpJFAENGP3v3Mc5i1fWOeO20Q\nlr2ovi8oYtkYyGpHvXcjUSRT1jJBKxVdfuvwBYXL++4GCKK5bgY2hvaGaA34\nUR8pDKnUU9p/lvJM+EkztsTy+J7L3XznngYREW64zVXeF28674Zrd+YrjNLL\nA3Zz6zGE8aV2tOluF4UiGAdk15Gx87TJ9+gj1q30eASlkBW+ta+pTPGaCEi+\nQlymGFPDvPziIhVw0uZHuyIsZj3Drt50YukS+4++04fzOapheFCAQMcw/nF/\nyZ1xCp0/v7nQ+554zrAZtHwQvJf6KfsLTDBc927/OyazsRgRZDtvKBCGlEZ7\nfuUNUUkwQhY6dMCDAZrUhNI7n66NZ7NyzBufZb9I0MP0Ag03YCj8Q9ngaNnB\nGjGW\r\n=KR+z\r\n-----END PGP SIGNATURE-----\r\n"},"maintainers":[{"name":"daviddias","email":"daviddias.p@gmail.com"},{"name":"dignifiedquire","email":"dignifiedquire@gmail.com"},{"name":"vmx","email":"volker.mische@gmail.com"}],"directories":{},"_npmOperationalInternal":{"host":"s3://npm-registry-packages","tmp":"tmp/multihashing-async_0.5.0_1525683193304_0.7975128776925684"}},"0.5.1":{"name":"multihashing-async","version":"0.5.1","description":"multiple hash functions","main":"src/index.js","browser":{"./src/crypto-sha1-2.js":"./src/crypto-sha1-2-browser.js"},"scripts":{"test":"aegir test","test:browser":"aegir test -t browser","test:node":"aegir test -t node","lint":"aegir lint","docs":"aegir docs","release":"aegir release --docs","release-minor":"aegir release --type minor --docs","release-major":"aegir release --type major --docs","build":"aegir build","coverage":"aegir coverage","coverage-publish":"aegir coverage publish","bench":"node benchmarks/hash.js"},"pre-commit":["lint","test"],"repository":{"type":"git","url":"git://github.com/multiformats/js-multihashing-async.git"},"keywords":["multihash"],"author":{"name":"Juan Benet","email":"juan@benet.ai","url":"http://juan.benet.ai/"},"license":"MIT","bugs":{"url":"https://github.com/multiformats/js-multihashing-async/issues"},"dependencies":{"async":"^2.6.1","blakejs":"^1.1.0","js-sha3":"^0.7.0","multihashes":"~0.4.13","murmurhash3js":"^3.0.1","nodeify":"^1.0.1"},"devDependencies":{"aegir":"^13.1.0","benchmark":"^2.1.4","chai":"^4.1.2","dirty-chai":"^2.0.1","pre-commit":"^1.2.2"},"engines":{"node":">=6.0.0","npm":">=3.0.0"},"homepage":"https://github.com/multiformats/js-multihashing-async","contributors":[{"name":"David Dias","email":"daviddias.p@gmail.com"},{"name":"David Dias","email":"mail@daviddias.me"},{"name":"Dmitriy Ryajov","email":"dryajov@gmail.com"},{"name":"Friedel Ziegelmayer","email":"dignifiedquire@gmail.com"},{"name":"Harlan T Wood","email":"harlantwood@users.noreply.github.com"},{"name":"Juan Batiz-Benet","email":"juan@benet.ai"},{"name":"Marcin Rataj","email":"lidel@lidel.org"},{"name":"Mitar","email":"mitar.github@tnode.com"},{"name":"Pedro Teixeira","email":"i@pgte.me"},{"name":"Richard Littauer","email":"richard.littauer@gmail.com"},{"name":"Richard Schneider","email":"makaretu@gmail.com"},{"name":"Victor Bjelkholm","email":"victorbjelkholm@gmail.com"},{"name":"Volker Mische","email":"volker.mische@gmail.com"},{"name":"npm-to-cdn-bot","email":"npmcdn-to-unpkg-bot@users.noreply.github.com","url":"by Forbes Lindesay"}],"gitHead":"d0394fe8a935ccc0b559a9a398871e5730d7a6a8","_id":"multihashing-async@0.5.1","_npmVersion":"5.6.0","_nodeVersion":"8.11.1","_npmUser":{"name":"daviddias","email":"mail@daviddias.me"},"dist":{"integrity":"sha512-Ft5lQNcJCfsns1QN1TDXqPZrrNwBYqIokprYJR2h2Jj01x0GFcYmJYAqHvme6vJoyI3XptEcmZpdr9g5Oy7q3Q==","shasum":"1fc563798f3777b43df0f77a0bf6474192687c0c","tarball":"https://registry.npmjs.org/multihashing-async/-/multihashing-async-0.5.1.tgz","fileCount":19,"unpackedSize":496057,"npm-signature":"-----BEGIN PGP SIGNATURE-----\r\nVersion: OpenPGP.js v3.0.4\r\nComment: https://openpgpjs.org\r\n\r\nwsFcBAEBCAAQBQJbDlx2CRA9TVsSAnZWagAA4D4P/Rt72i79rJDWpGiCYVlU\nq/KNLq0QXB7g7xAT/3OcKSKhNH/OH2fEVgLAhFe2y2+Ig4vCy5Qb3ximYn43\nI+1ZVleleacr8sMWPFtXxiRw8vINxki8FV31+/SiyPoU4TnUyfcDg5u+l8BI\nzvd3rLBa3ha/XYf1cpA6kM+x2HN31Zrry/wl+alBbT62Ul2CkrMUCzyo6Ayo\n21e8t927JURZJ55A+IUIVFI5UcE109HcnHjnwQOS1dJJGqsnpZjM0FucUCo+\nFtdoNXqagM4tpp80/HUDXwwHrbpB5SUBzRaAfm79Zg9B5HelcvghMzp0nExb\nkuHn5T9NyZijCk7ufkiA/Oq8495v05iZSTNK0A1I0/Pc5zFEVosZYLZAYy2A\nlF+o4K6fOXYAjE3qwS7dSWFZyg2KG8FcqkZNOmIsiu+QmFWO9JrzBh5Cj84t\nrisVRRaBJe0nt0C1NjvSqHms/a49JQDh/roVKuUGEiFQAVHoEv99snqFOtIx\nzEL7J59zl7o3nPTohJQuKc6teoy8MJFSLUsovoS7pKTojmdtsTERSyy/J0Rf\nL5S472po46IVvMDhzsDZpzGbMjZc+EtyeEjqTWlr4hWGu4fjaTSiOH7kOy4F\nPE7TVhlerp6oV4fJkw90397ebc7+ulxcPThVHCs5yuui5uYwKNdTWArvSgv3\nO3Zz\r\n=JH/Y\r\n-----END PGP SIGNATURE-----\r\n"},"maintainers":[{"name":"daviddias","email":"daviddias.p@gmail.com"},{"name":"dignifiedquire","email":"dignifiedquire@gmail.com"},{"name":"vmx","email":"volker.mische@gmail.com"}],"directories":{},"_npmOperationalInternal":{"host":"s3://npm-registry-packages","tmp":"tmp/multihashing-async_0.5.1_1527667829511_0.007200935557983401"}}},"readme":"# js-multihashing-async\n\n[![](https://img.shields.io/badge/made%20by-Protocol%20Labs-blue.svg?style=flat-square)](http://ipn.io)\n[![](https://img.shields.io/badge/project-multiformats-blue.svg?style=flat-square)](https://github.com/multiformats/multiformats)\n[![](https://img.shields.io/badge/freenode-%23ipfs-blue.svg?style=flat-square)](https://webchat.freenode.net/?channels=%23ipfs)\n[![Coverage Status](https://coveralls.io/repos/github/multiformats/js-multihashing-async/badge.svg?branch=master)](https://coveralls.io/github/multiformats/js-multihashing-async?branch=master)\n[![Travis CI](https://img.shields.io/travis/multiformats/js-multihashing-async.svg?style=flat-square&branch=master)](https://travis-ci.org/multiformats/js-multihashing-async)\n[![Circle CI](https://circleci.com/gh/multiformats/js-multihashing-async.svg?style=svg)](https://circleci.com/gh/multiformats/js-multihashing-async)\n[![Dependency Status](https://david-dm.org/multiformats/js-multihashing-async.svg?style=flat-square)](https://david-dm.org/multiformats/js-multihashing-async) \n[![js-standard-style](https://img.shields.io/badge/code%20style-standard-brightgreen.svg?style=flat-square)](https://github.com/feross/standard)\n![](https://img.shields.io/badge/npm-%3E%3D3.0.0-orange.svg?style=flat-square)\n![](https://img.shields.io/badge/Node.js-%3E%3D4.0.0-orange.svg?style=flat-square)\n[![](https://img.shields.io/badge/readme%20style-standard-brightgreen.svg?style=flat-square)](https://github.com/RichardLitt/standard-readme)\n\n> Use all the functions in [multihash](https://github.com/multiformats/multihash).\n\n#### Wait, why, how is this different from Node `crypto`?\n\nThis module just makes working with multihashes a bit nicer.\n[js-multihash](//github.com/multiformats/js-multihash) is only for\nencoding/decoding multihashes, and does not depend on other libs.\nThis module will depend on various implementations for each hash.\nIt currently uses `crypto` and [`sha3`](https://github.com/phusion/node-sha3) in Node.js.\nIn the browser [`webcrypto`](https://developer.mozilla.org/en-US/docs/Web/API/SubtleCrypto)\nand [`browserify-sha3`](https://github.com/wanderer/browserify-sha3) are used.\n\n## Table of Contents\n\n* [Table of Contents](#table-of-contents)\n* [Install](#install)\n  + [In Node.js through npm](#in-nodejs-through-npm)\n  + [Use in a browser with browserify, webpack or any other bundler](#use-in-a-browser-with-browserify-webpack-or-any-other-bundler)\n  + [Use in a browser Using a script tag](#use-in-a-browser-using-a-script-tag)\n    - [Gotchas](#gotchas)\n* [Usage](#usage)\n* [Examples](#examples)\n  + [Multihash output](#multihash-output)\n* [API](#api)\n* [Maintainers](#maintainers)\n* [Contribute](#contribute)\n* [License](#license)\n\n## Install\n\n### In Node.js through npm\n\n```bash\n$ npm install --save multihashing-async\n```\n\n```js\nconst multihashing = require('multihashing-async')\n```\n\n### Use in a browser with browserify, webpack or any other bundler\n\nThe code published to npm that gets loaded on require is in fact a ES5 transpiled\nversion with the right shims added. This means that you can require it and use with\nyour favourite bundler without having to adjust asset management process.\n\n```js\nconst multihashing = require('multihashing-async')\n```\n\n### Use in a browser Using a script tag\n\nLoading this module through a script tag will make the `multihashing` obj\navailable in the global namespace.\n\n```html\n<script src=\"https://unpkg.com/multihashing-async/dist/index.min.js\"></script>\n<!-- OR -->\n<script src=\"https://unpkg.com/multihashing-async/dist/index.js\"></script>\n```\n\n#### Gotchas\n\nYou will need to use Node.js `Buffer` API compatible, if you are running inside the browser, you can access it by `multihashing.Buffer` or you can install Feross's [Buffer](https://github.com/feross/buffer).\n\n## Usage\n\n```js\nconst multihashing = require('multihashing-async')\nconst buf = new Buffer('beep boop')\n\nmultihashing(buf, 'sha1', (err, multihash) => {\n  // by default calls back with a multihash.\n})\n\n// Use `.digest(...)` if you want only the hash digest (drops the prefix indicating the hash type).\nmultihashing.digest(buf, 'sha1', (err , digest) => {\n  // digest is the raw digest\n})\n\n// Use `.createHash(...)` for the raw hash functions\nconst h = multihashing.createHash('sha1')\nh(buf, (err, digest) => {\n  // digest is a buffer of the sha1 of buf\n})\n```\n\n## Examples\n\n### Multihash output\n\n```js\n> const multihashing = require('multihashing-async')\n> const buf = new Buffer('beep boop')\n\n> multihashing(buf, 'sha1', (err, mh) => console.log(mh))\n// => <Buffer 11 14 7c 83 57 57 7f 51 d4 f0 a8 d3 93 aa 1a aa fb 28 86 3d 94 21>\n\n> multihashing(buf, 'sha2-256', (err, mh) => console.log(mh))\n// => <Buffer 12 20 90 ea 68 8e 27 5d 58 05 67 32 50 32 49 2b 59 7b c7 72 21 c6 24 93 e7 63 30 b8 5d dd a1 91 ef 7c>\n\n> multihashing(buf, 'sha2-512', (err, mh) => console.log(mh))\n// => <Buffer 13 40 14 f3 01 f3 1b e2 43 f3 4c 56 68 93 78 83 77 1f a3 81 00 2f 1a aa 5f 31 b3 f7 8e 50 0b 66 ff 2f 4f 8e a5 e3 c9 f5 a6 1b d0 73 e2 45 2c 48 04 84 b0 ...>\n```\n\n## API\n\nhttps://multiformats.github.io/js-multihashing-async/\n\n## Maintainers\n\nCaptain: [@diasdavid](https://github.com/diasdavid).\n\n## Contribute\n\nContributions welcome. Please check out [the issues](https://github.com/multiformats/js-multihashing-async/issues).\n\nCheck out our [contributing document](https://github.com/multiformats/multiformats/blob/master/contributing.md) for more information on how we work, and about contributing in general. Please be aware that all interactions related to multiformats are subject to the IPFS [Code of Conduct](https://github.com/ipfs/community/blob/master/code-of-conduct.md).\n\nSmall note: If editing the README, please conform to the [standard-readme](https://github.com/RichardLitt/standard-readme) specification.\n\n## License\n\n[MIT](LICENSE) © 2016 Protocol Labs Inc.\n","maintainers":[{"name":"daviddias","email":"daviddias.p@gmail.com"},{"name":"dignifiedquire","email":"dignifiedquire@gmail.com"},{"name":"vmx","email":"volker.mische@gmail.com"}],"time":{"modified":"2018-05-30T08:10:36.668Z","created":"2016-10-01T11:08:29.257Z","0.1.0":"2016-10-01T11:08:29.257Z","0.2.0":"2016-11-03T07:39:39.753Z","0.3.0":"2016-11-29T17:03:03.616Z","0.4.0":"2017-01-27T11:14:02.255Z","0.4.1":"2017-02-08T21:08:08.487Z","0.4.2":"2017-02-09T15:51:08.772Z","0.4.3":"2017-02-24T11:52:49.726Z","0.4.4":"2017-03-16T15:12:31.469Z","0.4.5":"2017-03-23T12:32:24.277Z","0.4.6":"2017-07-21T16:14:28.615Z","0.4.7":"2017-10-20T11:54:24.178Z","0.4.8":"2018-02-27T11:58:38.242Z","0.4.9":"2018-05-07T08:50:59.906Z","0.5.0":"2018-05-07T08:53:13.396Z","0.5.1":"2018-05-30T08:10:29.583Z"},"homepage":"https://github.com/multiformats/js-multihashing-async","keywords":["multihash"],"repository":{"type":"git","url":"git://github.com/multiformats/js-multihashing-async.git"},"contributors":[{"name":"David Dias","email":"daviddias.p@gmail.com"},{"name":"David Dias","email":"mail@daviddias.me"},{"name":"Dmitriy Ryajov","email":"dryajov@gmail.com"},{"name":"Friedel Ziegelmayer","email":"dignifiedquire@gmail.com"},{"name":"Harlan T Wood","email":"harlantwood@users.noreply.github.com"},{"name":"Juan Batiz-Benet","email":"juan@benet.ai"},{"name":"Marcin Rataj","email":"lidel@lidel.org"},{"name":"Mitar","email":"mitar.github@tnode.com"},{"name":"Pedro Teixeira","email":"i@pgte.me"},{"name":"Richard Littauer","email":"richard.littauer@gmail.com"},{"name":"Richard Schneider","email":"makaretu@gmail.com"},{"name":"Victor Bjelkholm","email":"victorbjelkholm@gmail.com"},{"name":"Volker Mische","email":"volker.mische@gmail.com"},{"name":"npm-to-cdn-bot","email":"npmcdn-to-unpkg-bot@users.noreply.github.com","url":"by Forbes Lindesay"}],"author":{"name":"Juan Benet","email":"juan@benet.ai","url":"http://juan.benet.ai/"},"bugs":{"url":"https://github.com/multiformats/js-multihashing-async/issues"},"license":"MIT","readmeFilename":"README.md","_attachments":{},"_etag":"W/\"730f715078212e76021308da539a7259\"","_lastModified":"Wed, 30 May 2018 08:12:27 GMT","_cached":true}