{"_id":"split2","_rev":"34-ca7f9625e95a85338c8f505eca70e2b3","name":"split2","description":"split a Text Stream into a Line Stream, using Stream 3","dist-tags":{"latest":"3.0.0"},"versions":{"0.1.0":{"name":"split2","version":"0.1.0","description":"split a Text Stream into a Line Stream, using Stream 2","main":"index.js","scripts":{"test":"tap test.js"},"pre-commit":["test"],"website":"https://github.com/mcollina/split2","repository":{"type":"git","url":"https://github.com/mcollina/split2.git"},"bugs":{"url":"http://github.com/mcollina/split2/issues"},"author":{"name":"Matteo Collina","email":"hello@matteocollina.com"},"license":"ISC","devDependencies":{"tap":"~0.4.8","pre-commit":"0.0.4","callback-stream":"~1.0.2"},"dependencies":{"through2":"~0.4.1"},"homepage":"https://github.com/mcollina/split2","_id":"split2@0.1.0","dist":{"shasum":"83db2ac957b3b486e52922b3758974f94aa7c888","tarball":"https://registry.npmjs.org/split2/-/split2-0.1.0.tgz"},"_from":".","_npmVersion":"1.3.24","_npmUser":{"name":"matteo.collina","email":"hello@matteocollina.com"},"maintainers":[{"name":"matteo.collina","email":"hello@matteocollina.com"}],"directories":{}},"0.1.1":{"name":"split2","version":"0.1.1","description":"split a Text Stream into a Line Stream, using Stream 2","main":"index.js","scripts":{"test":"tap test.js"},"pre-commit":["test"],"website":"https://github.com/mcollina/split2","repository":{"type":"git","url":"https://github.com/mcollina/split2.git"},"bugs":{"url":"http://github.com/mcollina/split2/issues"},"author":{"name":"Matteo Collina","email":"hello@matteocollina.com"},"license":"ISC","devDependencies":{"tap":"~0.4.8","pre-commit":"0.0.4","callback-stream":"~1.0.2"},"dependencies":{"through2":"~0.4.1"},"homepage":"https://github.com/mcollina/split2","_id":"split2@0.1.1","dist":{"shasum":"c02398814057a724fddd0ed44257195a72d2b86a","tarball":"https://registry.npmjs.org/split2/-/split2-0.1.1.tgz"},"_from":".","_npmVersion":"1.3.24","_npmUser":{"name":"matteo.collina","email":"hello@matteocollina.com"},"maintainers":[{"name":"matteo.collina","email":"hello@matteocollina.com"}],"directories":{}},"0.1.2":{"name":"split2","version":"0.1.2","description":"split a Text Stream into a Line Stream, using Stream 2","main":"index.js","scripts":{"test":"tap test.js"},"pre-commit":["test"],"website":"https://github.com/mcollina/split2","repository":{"type":"git","url":"https://github.com/mcollina/split2.git"},"bugs":{"url":"http://github.com/mcollina/split2/issues"},"author":{"name":"Matteo Collina","email":"hello@matteocollina.com"},"license":"ISC","devDependencies":{"tap":"~0.4.8","pre-commit":"0.0.4","callback-stream":"~1.0.2"},"dependencies":{"through2":"~0.4.1"},"homepage":"https://github.com/mcollina/split2","_id":"split2@0.1.2","_shasum":"a4d560b91f04168f21cd9bdd569b6f78d5164593","_from":".","_npmVersion":"1.4.9","_npmUser":{"name":"matteo.collina","email":"hello@matteocollina.com"},"maintainers":[{"name":"matteo.collina","email":"hello@matteocollina.com"}],"dist":{"shasum":"a4d560b91f04168f21cd9bdd569b6f78d5164593","tarball":"https://registry.npmjs.org/split2/-/split2-0.1.2.tgz"},"directories":{}},"0.2.0":{"name":"split2","version":"0.2.0","description":"split a Text Stream into a Line Stream, using Stream 2","main":"index.js","scripts":{"test":"tap test.js"},"pre-commit":["test"],"website":"https://github.com/mcollina/split2","repository":{"type":"git","url":"https://github.com/mcollina/split2.git"},"bugs":{"url":"http://github.com/mcollina/split2/issues"},"author":{"name":"Matteo Collina","email":"hello@matteocollina.com"},"license":"ISC","devDependencies":{"tap":"~0.4.12","pre-commit":"0.0.9","callback-stream":"~1.0.2"},"dependencies":{"through2":"~0.6.0"},"homepage":"https://github.com/mcollina/split2","_id":"split2@0.2.0","_shasum":"f70f4f2ccfeb257e93568c62c9cbb21420ae7e24","_from":".","_npmVersion":"1.4.9","_npmUser":{"name":"matteo.collina","email":"hello@matteocollina.com"},"maintainers":[{"name":"matteo.collina","email":"hello@matteocollina.com"}],"dist":{"shasum":"f70f4f2ccfeb257e93568c62c9cbb21420ae7e24","tarball":"https://registry.npmjs.org/split2/-/split2-0.2.0.tgz"},"directories":{}},"0.2.1":{"name":"split2","version":"0.2.1","description":"split a Text Stream into a Line Stream, using Stream 2","main":"index.js","scripts":{"test":"tap test.js"},"pre-commit":["test"],"website":"https://github.com/mcollina/split2","repository":{"type":"git","url":"https://github.com/mcollina/split2.git"},"bugs":{"url":"http://github.com/mcollina/split2/issues"},"author":{"name":"Matteo Collina","email":"hello@matteocollina.com"},"license":"ISC","devDependencies":{"tap":"~0.4.12","pre-commit":"0.0.9","callback-stream":"~1.0.2"},"dependencies":{"through2":"~0.6.1"},"homepage":"https://github.com/mcollina/split2","_id":"split2@0.2.1","_shasum":"02ddac9adc03ec0bb78c1282ec079ca6e85ae900","_from":".","_npmVersion":"1.4.9","_npmUser":{"name":"matteo.collina","email":"hello@matteocollina.com"},"maintainers":[{"name":"matteo.collina","email":"hello@matteocollina.com"}],"dist":{"shasum":"02ddac9adc03ec0bb78c1282ec079ca6e85ae900","tarball":"https://registry.npmjs.org/split2/-/split2-0.2.1.tgz"},"directories":{}},"1.0.0":{"name":"split2","version":"1.0.0","description":"split a Text Stream into a Line Stream, using Stream 3","main":"index.js","scripts":{"test":"tap test.js"},"pre-commit":["test"],"website":"https://github.com/mcollina/split2","repository":{"type":"git","url":"git+https://github.com/mcollina/split2.git"},"bugs":{"url":"http://github.com/mcollina/split2/issues"},"author":{"name":"Matteo Collina","email":"hello@matteocollina.com"},"license":"ISC","devDependencies":{"tap":"~0.4.12","pre-commit":"0.0.9","callback-stream":"~1.0.2"},"dependencies":{"through2":"~2.0.0"},"gitHead":"f0755305c3c47faac7b5b059543a821894944c23","homepage":"https://github.com/mcollina/split2#readme","_id":"split2@1.0.0","_shasum":"52e2e221d88c75f9a73f90556e263ff96772b314","_from":".","_npmVersion":"2.9.1","_nodeVersion":"0.12.3","_npmUser":{"name":"matteo.collina","email":"hello@matteocollina.com"},"dist":{"shasum":"52e2e221d88c75f9a73f90556e263ff96772b314","tarball":"https://registry.npmjs.org/split2/-/split2-1.0.0.tgz"},"maintainers":[{"name":"matteo.collina","email":"hello@matteocollina.com"}],"directories":{}},"1.1.0":{"name":"split2","version":"1.1.0","description":"split a Text Stream into a Line Stream, using Stream 3","main":"index.js","scripts":{"test":"tap test.js"},"pre-commit":["test"],"website":"https://github.com/mcollina/split2","repository":{"type":"git","url":"git+https://github.com/mcollina/split2.git"},"bugs":{"url":"http://github.com/mcollina/split2/issues"},"author":{"name":"Matteo Collina","email":"hello@matteocollina.com"},"license":"ISC","devDependencies":{"tap":"~0.4.12","pre-commit":"0.0.9","callback-stream":"~1.0.2"},"dependencies":{"through2":"~2.0.0"},"gitHead":"bd01e1b0ce1f33409cd57d9805aaf09c8386f5af","homepage":"https://github.com/mcollina/split2#readme","_id":"split2@1.1.0","_shasum":"bd970913fc41814430bff5b9d72e7978d140a98b","_from":".","_npmVersion":"3.4.1","_nodeVersion":"4.2.0","_npmUser":{"name":"matteo.collina","email":"hello@matteocollina.com"},"dist":{"shasum":"bd970913fc41814430bff5b9d72e7978d140a98b","tarball":"https://registry.npmjs.org/split2/-/split2-1.1.0.tgz"},"maintainers":[{"name":"matteo.collina","email":"hello@matteocollina.com"}],"directories":{}},"1.1.1":{"name":"split2","version":"1.1.1","description":"split a Text Stream into a Line Stream, using Stream 3","main":"index.js","scripts":{"test":"tap test.js"},"pre-commit":["test"],"website":"https://github.com/mcollina/split2","repository":{"type":"git","url":"git+https://github.com/mcollina/split2.git"},"bugs":{"url":"http://github.com/mcollina/split2/issues"},"author":{"name":"Matteo Collina","email":"hello@matteocollina.com"},"license":"ISC","devDependencies":{"tap":"~0.4.12","pre-commit":"0.0.9","callback-stream":"~1.0.2"},"dependencies":{"through2":"~2.0.0"},"gitHead":"1a65c8cf7b70bfc6e6e234091380aaebf97e7c50","homepage":"https://github.com/mcollina/split2#readme","_id":"split2@1.1.1","_shasum":"162d9b18865f02ab2f2ad9585522db9b54c481f9","_from":".","_npmVersion":"3.4.1","_nodeVersion":"4.2.0","_npmUser":{"name":"matteo.collina","email":"hello@matteocollina.com"},"dist":{"shasum":"162d9b18865f02ab2f2ad9585522db9b54c481f9","tarball":"https://registry.npmjs.org/split2/-/split2-1.1.1.tgz"},"maintainers":[{"name":"matteo.collina","email":"hello@matteocollina.com"}],"directories":{}},"2.0.0":{"name":"split2","version":"2.0.0","description":"split a Text Stream into a Line Stream, using Stream 3","main":"index.js","scripts":{"test":"standard && tap -b test.js"},"pre-commit":["test"],"website":"https://github.com/mcollina/split2","repository":{"type":"git","url":"git+https://github.com/mcollina/split2.git"},"bugs":{"url":"http://github.com/mcollina/split2/issues"},"author":{"name":"Matteo Collina","email":"hello@matteocollina.com"},"license":"ISC","devDependencies":{"callback-stream":"^1.1.0","fastbench":"^1.0.0","pre-commit":"^1.1.2","standard":"^5.4.1","tap":"^5.0.0"},"dependencies":{"through2":"~2.0.0"},"gitHead":"11eab80618c394e36bead733a6185e1576fe62e6","homepage":"https://github.com/mcollina/split2#readme","_id":"split2@2.0.0","_shasum":"bab4446f94025f19ea6e4b9dba8e16e8053468fa","_from":".","_npmVersion":"2.14.12","_nodeVersion":"4.2.4","_npmUser":{"name":"matteo.collina","email":"hello@matteocollina.com"},"dist":{"shasum":"bab4446f94025f19ea6e4b9dba8e16e8053468fa","tarball":"https://registry.npmjs.org/split2/-/split2-2.0.0.tgz"},"maintainers":[{"name":"matteo.collina","email":"hello@matteocollina.com"}],"directories":{}},"2.0.1":{"name":"split2","version":"2.0.1","description":"split a Text Stream into a Line Stream, using Stream 3","main":"index.js","scripts":{"test":"standard && tap -b test.js"},"pre-commit":["test"],"website":"https://github.com/mcollina/split2","repository":{"type":"git","url":"git+https://github.com/mcollina/split2.git"},"bugs":{"url":"http://github.com/mcollina/split2/issues"},"author":{"name":"Matteo Collina","email":"hello@matteocollina.com"},"license":"ISC","devDependencies":{"callback-stream":"^1.1.0","fastbench":"^1.0.0","pre-commit":"^1.1.2","standard":"^5.4.1","tap":"^5.0.0"},"dependencies":{"through2":"~2.0.0"},"gitHead":"489fd6c272a8f03970c28df03c303df8a9356b9d","homepage":"https://github.com/mcollina/split2#readme","_id":"split2@2.0.1","_shasum":"a01f8e46b7d56145193af845249bfe7c070c5260","_from":".","_npmVersion":"2.14.12","_nodeVersion":"4.2.4","_npmUser":{"name":"matteo.collina","email":"hello@matteocollina.com"},"dist":{"shasum":"a01f8e46b7d56145193af845249bfe7c070c5260","tarball":"https://registry.npmjs.org/split2/-/split2-2.0.1.tgz"},"maintainers":[{"name":"matteo.collina","email":"hello@matteocollina.com"}],"_npmOperationalInternal":{"host":"packages-5-east.internal.npmjs.com","tmp":"tmp/split2-2.0.1.tgz_1454755495672_0.8937675757333636"},"directories":{}},"2.1.0":{"name":"split2","version":"2.1.0","description":"split a Text Stream into a Line Stream, using Stream 3","main":"index.js","scripts":{"test":"standard && tap -b test.js"},"pre-commit":["test"],"website":"https://github.com/mcollina/split2","repository":{"type":"git","url":"git+https://github.com/mcollina/split2.git"},"bugs":{"url":"http://github.com/mcollina/split2/issues"},"author":{"name":"Matteo Collina","email":"hello@matteocollina.com"},"license":"ISC","devDependencies":{"callback-stream":"^1.1.0","fastbench":"^1.0.0","pre-commit":"^1.1.2","standard":"^7.0.0","tap":"^5.0.0"},"dependencies":{"through2":"~2.0.0"},"gitHead":"a963dadb05c7cf0cbe77e4e1eb815c672100bb65","homepage":"https://github.com/mcollina/split2#readme","_id":"split2@2.1.0","_shasum":"7382c148cb622c4b28af7c727f9673730b73f474","_from":".","_npmVersion":"2.15.0","_nodeVersion":"4.4.2","_npmUser":{"name":"matteo.collina","email":"hello@matteocollina.com"},"dist":{"shasum":"7382c148cb622c4b28af7c727f9673730b73f474","tarball":"https://registry.npmjs.org/split2/-/split2-2.1.0.tgz"},"maintainers":[{"name":"matteo.collina","email":"hello@matteocollina.com"}],"_npmOperationalInternal":{"host":"packages-12-west.internal.npmjs.com","tmp":"tmp/split2-2.1.0.tgz_1463677902226_0.7877608684357256"},"directories":{}},"2.1.1":{"name":"split2","version":"2.1.1","description":"split a Text Stream into a Line Stream, using Stream 3","main":"index.js","scripts":{"test":"standard && tap -b test.js"},"pre-commit":["test"],"website":"https://github.com/mcollina/split2","repository":{"type":"git","url":"git+https://github.com/mcollina/split2.git"},"bugs":{"url":"http://github.com/mcollina/split2/issues"},"author":{"name":"Matteo Collina","email":"hello@matteocollina.com"},"license":"ISC","devDependencies":{"callback-stream":"^1.1.0","fastbench":"^1.0.0","pre-commit":"^1.1.2","standard":"^8.6.0","tap":"^8.0.1"},"dependencies":{"through2":"^2.0.2"},"gitHead":"5a9787350f4685fc2d9af9eedddf487d4a6710d6","homepage":"https://github.com/mcollina/split2#readme","_id":"split2@2.1.1","_shasum":"7a1f551e176a90ecd3345f7246a0cfe175ef4fd0","_from":".","_npmVersion":"3.10.9","_nodeVersion":"6.9.2","_npmUser":{"name":"matteo.collina","email":"hello@matteocollina.com"},"dist":{"shasum":"7a1f551e176a90ecd3345f7246a0cfe175ef4fd0","tarball":"https://registry.npmjs.org/split2/-/split2-2.1.1.tgz"},"maintainers":[{"name":"matteo.collina","email":"hello@matteocollina.com"}],"_npmOperationalInternal":{"host":"packages-18-east.internal.npmjs.com","tmp":"tmp/split2-2.1.1.tgz_1483345766693_0.20675289118662477"},"directories":{}},"2.2.0":{"name":"split2","version":"2.2.0","description":"split a Text Stream into a Line Stream, using Stream 3","main":"index.js","scripts":{"test":"standard && tap -b test.js"},"pre-commit":["test"],"website":"https://github.com/mcollina/split2","repository":{"type":"git","url":"git+https://github.com/mcollina/split2.git"},"bugs":{"url":"http://github.com/mcollina/split2/issues"},"author":{"name":"Matteo Collina","email":"hello@matteocollina.com"},"license":"ISC","devDependencies":{"callback-stream":"^1.1.0","fastbench":"^1.0.0","pre-commit":"^1.1.2","safe-buffer":"^5.1.1","standard":"^10.0.0","tap":"^10.0.0"},"dependencies":{"through2":"^2.0.2"},"gitHead":"ba1f582661a1ebb3b1f6ea4059c98bd9a73b7a11","homepage":"https://github.com/mcollina/split2#readme","_id":"split2@2.2.0","_npmVersion":"5.4.2","_nodeVersion":"6.11.1","_npmUser":{"name":"matteo.collina","email":"hello@matteocollina.com"},"dist":{"integrity":"sha512-RAb22TG39LhI31MbreBgIuKiIKhVsawfTgEGqKHTK87aG+ul/PB8Sqoi3I7kVdRWiCfrKxK3uo4/YUkpNvhPbw==","shasum":"186b2575bcf83e85b7d18465756238ee4ee42493","tarball":"https://registry.npmjs.org/split2/-/split2-2.2.0.tgz"},"maintainers":[{"name":"matteo.collina","email":"hello@matteocollina.com"}],"_npmOperationalInternal":{"host":"s3://npm-registry-packages","tmp":"tmp/split2-2.2.0.tgz_1506330790940_0.4804259219672531"},"directories":{}},"3.0.0":{"name":"split2","version":"3.0.0","description":"split a Text Stream into a Line Stream, using Stream 3","main":"index.js","scripts":{"test":"standard && tap -b test.js"},"pre-commit":["test"],"website":"https://github.com/mcollina/split2","repository":{"type":"git","url":"git+https://github.com/mcollina/split2.git"},"bugs":{"url":"http://github.com/mcollina/split2/issues"},"author":{"name":"Matteo Collina","email":"hello@matteocollina.com"},"license":"ISC","devDependencies":{"binary-split":"^1.0.3","callback-stream":"^1.1.0","fastbench":"^1.0.0","pre-commit":"^1.1.2","safe-buffer":"^5.1.1","standard":"^11.0.0","tap":"^12.0.0"},"dependencies":{"readable-stream":"^3.0.0"},"greenkeeper":{"ignore":["tap"]},"gitHead":"53c8b0a00e4280b38bfda40f7ecf0db4e70e341f","homepage":"https://github.com/mcollina/split2#readme","_id":"split2@3.0.0","_npmVersion":"6.3.0","_nodeVersion":"8.11.3","_npmUser":{"name":"matteo.collina","email":"hello@matteocollina.com"},"dist":{"integrity":"sha512-Cp7G+nUfKJyHCrAI8kze3Q00PFGEG1pMgrAlTFlDbn+GW24evSZHJuMl+iUJx1w/NTRDeBiTgvwnf6YOt94FMw==","shasum":"55057cd560687a7ef6464471597404577ff1735d","tarball":"https://registry.npmjs.org/split2/-/split2-3.0.0.tgz","fileCount":7,"unpackedSize":14370,"npm-signature":"-----BEGIN PGP SIGNATURE-----\r\nVersion: OpenPGP.js v3.0.4\r\nComment: https://openpgpjs.org\r\n\r\nwsFcBAEBCAAQBQJbcLCaCRA9TVsSAnZWagAAM6YP/3iasyTzA2xAaXK/vq9p\n3pyG4Zdne9x5ABrSH1/rmzhTFvFwJK7lgEmbrKsSNYok8vuJ941aprHhl/yP\nG6UcwMtmuXqn0a+h7ldYM6pvvxbARut37fWDs2eKsGZ1/rQrWMOv8d2IUkwb\nIOf4u1Kp0+u3rpPa8xcmr9if2YD/kLJqy9hzA+EQcufuhtduXIHmOMVtmHWC\nAwAbHz9MUBU0PiLF9h1+NlBwp/cceFB1GNCOyEwBQHDhay+FAj9/Xwq0j2rI\n1BtIXLOBI5Ute8ZduCMrM1/8JOqI7I32RonfJjE5m7yJLvjXE8FYAoLJ04DI\ntQTR+bmhR5krXaH2u8Xvnpec6Vjrxsp7J+Hs9PJTC4xAyUeRkH3NhfD+FbLH\n4HCGOIyUBn5caERtVhCjdDqa9+P9FIus+s+7w/rebD+KjGNu2+xJVKJ2geyb\ngw6wy7YLlEvaDiUbW6/Tnfj2MPxxQzNN1wZ0YhFiQ9TDmSAFHE9RmqEmFOOY\nmeboecAf5nmSynpMpE4dBpvGfwb4WRGJjalSaInYWtiW4j05wse1Y42IqWyk\nnovSumbz+LoonR/Cq2yXUoZ3C/YTQtVlZmF2Hj+aUE0UTwuieUD5jT93Yoo4\n4jk6tbfpMLEcqPrmfwQ0J8OJwADWQeIU49YUqtp5m6yOUUAMg/E3AXoDcCba\n2LPL\r\n=7Rax\r\n-----END PGP SIGNATURE-----\r\n"},"maintainers":[{"name":"matteo.collina","email":"hello@matteocollina.com"}],"directories":{},"_npmOperationalInternal":{"host":"s3://npm-registry-packages","tmp":"tmp/split2_3.0.0_1534111898054_0.9868726058710928"}}},"readme":"# Split2(matcher, mapper, options)\n\n[![Greenkeeper badge](https://badges.greenkeeper.io/mcollina/split2.svg)](https://greenkeeper.io/)\n\n[![build status](https://secure.travis-ci.org/mcollina/split2.svg)](http://travis-ci.org/mcollina/split2)\n\nBreak up a stream and reassemble it so that each line is a chunk.\n`split2` is inspired by [@dominictarr](https://github.com/dominictarr) [`split`](https://github.com/dominictarr/split) module,\nand it is totally API compatible with it.\nHowever, it is based on Node.js core [`Transform`](https://nodejs.org/api/stream.html#stream_new_stream_transform_options) via [`readable-stream`](https://github.com/nodejs/readable-stream)\n\n`matcher` may be a `String`, or a `RegExp`. Example, read every line in a file ...\n\n``` js\n  fs.createReadStream(file)\n    .pipe(split2())\n    .on('data', function (line) {\n      //each chunk now is a separate line!\n    })\n\n```\n\n`split` takes the same arguments as `string.split` except it defaults to '/\\r?\\n/', and the optional `limit` paremeter is ignored.\n[String#split](https://developer.mozilla.org/en/JavaScript/Reference/Global_Objects/String/split)\n\n`split` takes an optional options object on it's third argument, which\nis directly passed as a\n[Transform](https://nodejs.org/api/stream.html#stream_new_stream_transform_options)\noption.\n\nAdditionally, the `.maxLength` option is implemented, which will make the split stream throw an error\nif the buffer size exceeds `.maxLength`.\n\nCalling `.destroy` will make the stream emit `close`. Use this to perform cleanup logic\n\n``` js\nvar splitFile = function(filename) {\n  var file = fs.createReadStream(filename)\n\n  return file\n    .pipe(split2())\n    .on('close', function() {\n      // destroy the file stream in case the split stream was destroyed\n      file.destroy()\n    })\n}\n\nvar stream = splitFile('my-file.txt')\n\nstream.destroy() // will destroy the input file stream\n```\n\n# NDJ - Newline Delimited Json\n\n`split2` accepts a function which transforms each line.\n\n``` js\nfs.createReadStream(file)\n  .pipe(split2(JSON.parse))\n  .on('data', function (obj) {\n    //each chunk now is a js object\n  })\n```\n\nHowever, in [@dominictarr](https://github.com/dominictarr) [`split`](https://github.com/dominictarr/split) the mapper\nis wrapped in a try-catch, while here it is not: if your parsing logic can throw, wrap it yourself.\n\n# Benchmark\n\n```bash\n$ node bench.js\nbenchSplit*10000: 1484.983ms\nbenchBinarySplit*10000: 1484.080ms\nbenchSplit*10000: 1407.334ms\nbenchBinarySplit*10000: 1500.281ms\n```\n\nBenchmark taken on Node 8.11.3, on a Macbook i5 2018.\n\n# License\n\nCopyright (c) 2014-2018, Matteo Collina <hello@matteocollina.com>\n\nPermission to use, copy, modify, and/or distribute this software for any\npurpose with or without fee is hereby granted, provided that the above\ncopyright notice and this permission notice appear in all copies.\n\nTHE SOFTWARE IS PROVIDED \"AS IS\" AND THE AUTHOR DISCLAIMS ALL WARRANTIES\nWITH REGARD TO THIS SOFTWARE INCLUDING ALL IMPLIED WARRANTIES OF\nMERCHANTABILITY AND FITNESS. IN NO EVENT SHALL THE AUTHOR BE LIABLE FOR\nANY SPECIAL, DIRECT, INDIRECT, OR CONSEQUENTIAL DAMAGES OR ANY DAMAGES\nWHATSOEVER RESULTING FROM LOSS OF USE, DATA OR PROFITS, WHETHER IN AN\nACTION OF CONTRACT, NEGLIGENCE OR OTHER TORTIOUS ACTION, ARISING OUT OF OR\nIN CONNECTION WITH THE USE OR PERFORMANCE OF THIS SOFTWARE.\n","maintainers":[{"name":"matteo.collina","email":"hello@matteocollina.com"}],"time":{"modified":"2018-08-12T22:11:41.304Z","created":"2014-03-12T12:17:59.330Z","0.1.0":"2014-03-12T12:17:59.330Z","0.1.1":"2014-03-13T16:47:04.844Z","0.1.2":"2014-06-17T14:03:57.220Z","0.2.0":"2014-08-09T13:29:31.437Z","0.2.1":"2014-08-12T09:25:29.291Z","1.0.0":"2015-06-13T16:14:10.562Z","1.1.0":"2015-12-24T08:24:47.344Z","1.1.1":"2016-01-07T17:23:03.269Z","2.0.0":"2016-01-20T14:08:41.425Z","2.0.1":"2016-02-06T10:44:56.804Z","2.1.0":"2016-05-19T17:11:44.551Z","2.1.1":"2017-01-02T08:29:27.243Z","2.2.0":"2017-09-25T09:13:11.905Z","3.0.0":"2018-08-12T22:11:38.140Z"},"homepage":"https://github.com/mcollina/split2#readme","repository":{"type":"git","url":"git+https://github.com/mcollina/split2.git"},"author":{"name":"Matteo Collina","email":"hello@matteocollina.com"},"bugs":{"url":"http://github.com/mcollina/split2/issues"},"license":"ISC","readmeFilename":"README.md","users":{"timhudson":true,"matteo.collina":true,"zhangyaochun":true,"smerik":true,"barenko":true,"shanewholloway":true,"mugeso":true,"uh-engineer":true,"dzhou777":true,"seangenabe":true,"simon129":true,"kodekracker":true,"sheikhsajid":true},"_attachments":{},"_etag":"W/\"c08dd85502b05e012dc72a379fa0eba2\"","_lastModified":"Sun, 12 Aug 2018 22:11:42 GMT","_cached":true}